cachedx/__init__.py
cachedx/py.typed
cachedx/core/__init__.py
cachedx/core/duck.py
cachedx/core/llm.py
cachedx/core/safe_sql.py
cachedx/core/util.py
cachedx/httpcache/__init__.py
cachedx/httpcache/client.py
cachedx/httpcache/config.py
cachedx/httpcache/exceptions.py
cachedx/httpcache/key.py
cachedx/httpcache/storage.py
cachedx/mirror/__init__.py
cachedx/mirror/hooks.py
cachedx/mirror/inference.py
cachedx/mirror/normalize.py
cachedx/mirror/registry.py
cachedx-0.2.2.dist-info/METADATA
cachedx-0.2.2.dist-info/WHEEL
cachedx-0.2.2.dist-info/licenses/LICENSE
cachedx-0.2.2.dist-info/RECORD
