Metadata-Version: 2.4
Name: cachedx
Version: 0.2.2
Summary: Unified httpx cache (TTL/ETag) + DuckDB mirror (raw+normalized) with SQL/LLM helpers
Project-URL: Homepage, https://github.com/yourusername/cachedx
Project-URL: Documentation, https://cachedx.readthedocs.io
Project-URL: Repository, https://github.com/yourusername/cachedx
Project-URL: Issues, https://github.com/yourusername/cachedx/issues
Author-email: alywonder <al@yiwonder.com>
License: MIT
License-File: LICENSE
Keywords: api,cache,duckdb,httpx,json,llm,sql
Classifier: Development Status :: 5 - Production/Stable
Classifier: Intended Audience :: Developers
Classifier: License :: OSI Approved :: MIT License
Classifier: Programming Language :: Python :: 3
Classifier: Programming Language :: Python :: 3.12
Classifier: Topic :: Database
Classifier: Topic :: Internet :: WWW/HTTP
Classifier: Topic :: Software Development :: Libraries :: Python Modules
Classifier: Typing :: Typed
Requires-Python: >=3.12
Requires-Dist: duckdb>=1.0.0
Requires-Dist: httpx>=0.27.0
Requires-Dist: orjson>=3.10.0
Requires-Dist: pydantic-settings>=2.3.0
Requires-Dist: pydantic>=2.8.0
Requires-Dist: typing-extensions>=4.9.0
Provides-Extra: dev
Requires-Dist: ipython>=8.24.0; extra == 'dev'
Requires-Dist: mypy>=1.10.0; extra == 'dev'
Requires-Dist: pytest-asyncio>=0.23.0; extra == 'dev'
Requires-Dist: pytest-cov>=5.0.0; extra == 'dev'
Requires-Dist: pytest>=8.2.0; extra == 'dev'
Requires-Dist: respx>=0.21.0; extra == 'dev'
Requires-Dist: ruff>=0.13.2; extra == 'dev'
Requires-Dist: twine>=6.0.0; extra == 'dev'
Provides-Extra: docs
Requires-Dist: mkdocs-material>=9.5.0; extra == 'docs'
Requires-Dist: mkdocs-mermaid2-plugin>=1.1.0; extra == 'docs'
Requires-Dist: mkdocs>=1.6.0; extra == 'docs'
Requires-Dist: mkdocstrings[python]>=0.25.0; extra == 'docs'
Provides-Extra: pandas
Requires-Dist: pandas>=2.2.0; extra == 'pandas'
